{
  "date": "2026-05-20",
  "timestamp": "2026-05-20T22:11:02+00:00",
  "portfolio_return": 0.019511299539786316,
  "benchmark_return": 0.010792026370445518,
  "alpha": 0.008719273169340798,
  "position_returns": [
    {
      "ticker": "EVO.ST",
      "weight": 0.22,
      "return": 0.07263413800531282,
      "price": 711.7999877929688
    },
    {
      "ticker": "CRWD",
      "weight": 0.05,
      "return": 0.053867819034048026,
      "price": 650.1099853515625
    },
    {
      "ticker": "PANW",
      "weight": 0.15,
      "return": 0.027193597828324867,
      "price": 246.66000366210938
    },
    {
      "ticker": "FTNT",
      "weight": 0.17,
      "return": 0.01848950659383153,
      "price": 130.0
    },
    {
      "ticker": "CSCO",
      "weight": 0.18,
      "return": -0.008927013380270798,
      "price": 114.3499984741211
    },
    {
      "ticker": "HUM",
      "weight": 0.23,
      "return": -0.020769544173201093,
      "price": 304.1000061035156
    }
  ],
  "ai_recommendation": "Yes\u2014update the portfolio: keep EVO.ST, CRWD, and PANW (they\u2019re driving the outperformance), keep FTNT (positive but smaller), and drop CSCO and HUM (both negative and dragging). Reallocate the freed weight into EVO.ST/CRWD/PANW in proportion to their relative strength (heaviest on EVO.ST, then CRWD, then PANW).",
  "game_standing": {
    "rank": 1072,
    "total_players": 9117,
    "value_eur": 13179.18683989893,
    "today_return_pct": 0.441,
    "week_return_pct": -5.284,
    "month_return_pct": 23.399
  }
}